sohaotel/__init__.py
sohaotel/ext/__init__.py
sohaotel/ext/otel/__init__.py
sohaotel/ext/otel/trace_decorator/__init__.py
sohaotel/ext/otel/trace_exporter/__init__.py
opencensus_ext_soha_otel-1.0.6.8.dist-info/METADATA
opencensus_ext_soha_otel-1.0.6.8.dist-info/WHEEL
opencensus_ext_soha_otel-1.0.6.8.dist-info/namespace_packages.txt
opencensus_ext_soha_otel-1.0.6.8.dist-info/top_level.txt
opencensus_ext_soha_otel-1.0.6.8.dist-info/RECORD
